{
  "pluginList": [
    "nadavspi/obsidian-relative-line-numbers",
    "polyipseity/obsidian-show-hidden-files",
    "RAIT-09/obsidian-agent-client"
  ],
  "pluginSubListFrozenVersion": [
    {
      "repo": "nadavspi/obsidian-relative-line-numbers",
      "version": "latest"
    },
    {
      "repo": "polyipseity/obsidian-show-hidden-files",
      "version": "2.5.0"
    },
    {
      "repo": "RAIT-09/obsidian-agent-client",
      "version": "0.8.3"
    }
  ],
  "themesList": [],
  "updateAtStartup": false,
  "updateThemesAtStartup": false,
  "enableAfterInstall": true,
  "loggingEnabled": false,
  "loggingPath": "BRAT-log",
  "loggingVerboseEnabled": false,
  "debuggingMode": false,
  "notificationsEnabled": true,
  "globalTokenName": "",
  "personalAccessToken": "",
  "selectLatestPluginVersionByDefault": false,
  "allowIncompatiblePlugins": false
}